<?xml version="1.0" encoding="UTF-8"?>
<TEXTE_JURI_CONSTIT>
<META>
<META_COMMUN>
<ID>CONSTEXT000017665042</ID>
<ANCIEN_ID>CCO59AN00190</ANCIEN_ID>
<ORIGINE>CONSTIT</ORIGINE>
<URL>texte/juri/constit/CONS/TEXT/00/00/17/66/50/CONSTEXT000017665042.xml</URL>
<NATURE>AN</NATURE>
</META_COMMUN>
<META_SPEC>
<META_JURI>
<TITRE>A.N., Algérie (8ème circ.)</TITRE>
<DATE_DEC>1959-01-16</DATE_DEC>
<JURIDICTION>Conseil constitutionnel</JURIDICTION>
<NUMERO>58-190</NUMERO>
<SOLUTION>Rejet</SOLUTION>
</META_JURI>
<META_JURI_CONSTIT>
<NOR/>
<NATURE_QUALIFIEE>AN</NATURE_QUALIFIEE>
<LOI_DEF date="2999-01-01" nor="" num=""/>
<TITRE_JO>Journal officiel du 21 janvier 1959, p. 1124</TITRE_JO>
<URL_CC>http://www.conseil-constitutionnel.fr/decision/1959/58190an.htm</URL_CC>
<ECLI>ECLI:FR:CC:1959:58.190.AN</ECLI>
</META_JURI_CONSTIT>
</META_SPEC>
</META>
<TEXTE>
<BLOC_TEXTUEL>
<CONTENU>La Commission constitutionnelle provisoire,<br/>
<br/>Vu les articles 59 et 91 de la Constitution ;<br/>
Vu l'ordonnance du 7 novembre 1958 portant loi organique sur le Conseil constitutionnel, et notamment son article 38 ;<br/>
Vu la requête présentée par les sieurs VOITURIEZ (Albert-Jean), AGHA BENAISSA Rabah, LASSOULI MOULAY Ali, BARKAT Ahmed, CHAPUS (Maurice) et KENNANI Refas demeurant tous à Sidi-bel-Abbes, ladite requête enregistrée le 15 décembre 1958 au secrétariat de la Commission constitutionnelle provisoire et tendant à ce qu'il plaise à la Commission statuer sur les opérations électorales auxquelles il a été procédé les 28, 29 et 30 novembre 1958 dans la 6e circonscription d'Algérie pour la désignation de quatre députés à l'Assemblée nationale ;<br/>
Vu les autres pièces produites et jointes au dossier ;<br/>
Ouï le rapporteur en son rapport ;<br/>
<br/>1. Considérant qu'aux termes de l'article 33 de l'ordonnance du 7 novembre 1958 portant loi organique sur le Conseil constitutionnel, rendu applicable en vertu de l'article 57 de ladite ordonnance à la Commission constitutionnelle provisoire :<br/>
"L'élection d'un député ou d'un sénateur peut être contestée devant le Conseil constitutionnel durant les dix jours qui suivent la proclamation des résultats dudit scrutin" ; et qu'aux termes de l'article 34, de la même ordonnance ; "Le Conseil constitutionnel ne peut être saisi que par requête écrite adressée au secrétariat général du Conseil, au préfet ou au chef du territoire" ;<br/>
2. Considérant qu'il résulte de l'instruction que la proclamation des résultats du scrutin, du 30 novembre pour l'élection de quatre députés à l'Assemblée nationale dans la 8e circonscription d'Algérie a été faite le 2 décembre 1958 ; qu'ainsi le délai de dix jours fixé par l'article 33 précité de l'ordonnance du 7 novembre 1958 expirait le 12 décembre à minuit ;<br/>
3. Considérant qu'il ressort des pièces du dossier que les sieurs Voituriez, Agha Benaissa, Lassouli, Barkat, Chapus et Kennani n'ont pas usé de la faculté qui leur était donnée par l'article 31 susvisé de l'ordonnance du 7 novembre l958 pour déposer leur requête à la Préfecture ; qu'il est constant que ladite requête, adressée directement au secrétariat de la Commission constitutionnelle provisoire, n'y a été enregistrée que le 15 décembre, soit postérieurement a l'expiration du délai imparti ; que, dès lors, elle n'est pas recevable ;<br/>
<br/>Décide :<br/>
Article premier :<br/>
La requête susvisée des sieurs Voituriez (Albert-Jean), Agha Benaissa Rabah, Lassouli Moulay Ali, Barkat Ahmed, Chapus (Maurice) et Kennani est rejetée.<br/>
Article 2 :<br/>
La présente décision sera notifiée à l'Assemblée nationale et publiée au Journal officiel de la République française.         
</CONTENU>
</BLOC_TEXTUEL>
<SAISINES>
<CONTENU/>
</SAISINES>
<OBSERVATIONS>
<CONTENU/>
</OBSERVATIONS>
</TEXTE>
</TEXTE_JURI_CONSTIT>
