<?xml version="1.0" encoding="UTF-8"?>
<TEXTE_JURI_CONSTIT>
<META>
<META_COMMUN>
<ID>CONSTEXT000017664996</ID>
<ANCIEN_ID>CCO58AN00011</ANCIEN_ID>
<ORIGINE>CONSTIT</ORIGINE>
<URL>texte/juri/constit/CONS/TEXT/00/00/17/66/49/CONSTEXT000017664996.xml</URL>
<NATURE>AN</NATURE>
</META_COMMUN>
<META_SPEC>
<META_JURI>
<TITRE>A.N., Oise (4ème circ.)</TITRE>
<DATE_DEC>1958-12-04</DATE_DEC>
<JURIDICTION>Conseil constitutionnel</JURIDICTION>
<NUMERO>58-11/11bis</NUMERO>
<SOLUTION>Irrecevabilité</SOLUTION>
</META_JURI>
<META_JURI_CONSTIT>
<NOR/>
<NATURE_QUALIFIEE>AN</NATURE_QUALIFIEE>
<LOI_DEF date="2999-01-01" nor="" num=""/>
<TITRE_JO>Journal officiel du 7 décembre 1958, p. 11000</TITRE_JO>
<URL_CC>http://www.conseil-constitutionnel.fr/decision/1958/5811_11bisan.htm</URL_CC>
<ECLI>ECLI:FR:CC:1958:58.11.AN</ECLI>
</META_JURI_CONSTIT>
</META_SPEC>
</META>
<TEXTE>
<BLOC_TEXTUEL>
<CONTENU>La Commission constitutionnelle provisoire,<br/>
<br/>Vu les articles 59 et 91 de la Constitution;<br/>
Vu l'ordonnance du 7 novembre 1958 portant loi organique sur le Conseil constitutionnel;<br/>
Vu : 1° La contestation présentée par les sieurs Barre (André), Quintard (Albert), Richard (René), Diebolt (Hubert), Richard (Henri), Dupont (René), la dame Pierson, née Beaumont, le sieur Pierson (Robert), la demoiselle Fovet (Marguerite) et le sieur Tassin (Albert), ladite contestation insérée le 23 novembre 1958 au procès-verbal de recensement général des votes de la commune de Rozoy-en-Multien;<br/>
2° La contestation présentée par le sieur Olive, demeurant à Thury-en-Valois, ladite contestation insérée le 23  novembre  1958  au  procès-verbal  de recensement général des votes de la commune de Thury-en-Valois; lesdites protestations tendant à ce qu'il plaise à la Commission statuer sur les opérations électorales auxquelles il a été procédé le 23 novembre 1958 dans la 4° circonscription du département de l'Oise pour la désignation d'un député à l'Assemblée nationale;<br/>
Vu les autres pièces produites et jointes au dossier;<br/>
Ouï le rapporteur, en son rapport,<br/>
<br/>1. Considérant que les requêtes susvisées des sieurs Barre et autres, d'une part, et du sieur Olive, d'autre part, sont relatives aux mêmes opérations électorales, qu'il y a lieu de les joindre pour en faire l'obJet d'une seule décision;<br/>
2. Considérant qu'il résulte des dispositions de l'article 34 de l'ordonnance susvisée du 7 novembre 1958 portant loi organique sur le Conseil constitutionnel applicable à la Commission constitutionnelle provisoire en vertu de l'article 57 de la même ordonnance, que ladite Commission ne peut être saisie que par une requête écrite adressée au secrétariat général du Conseil, au préfet et au chef du territoire;<br/>
3. Considérant que les contestations susvisées du sieur Barre et autres, d'une part, et du sieur Olive, d'autre part, portées aux procès-verbaux de recensement des votes de deux communes de la circonscription, ne satisfont pas aux prescriptions susrappelées de l'article 34 de l'ordonnance susvisée du 7 novembre 1958;<br/>
que, dès lors, elles ne sont pas recevables;<br/>
<br/>Décide :<br/>
Article premier :<br/>
Les contestations des sieurs Barre, Quintard, Riechard (René), Diebolt (Hubert), Richard (Henri), Dupont (René), Pierson et Tassin et des dames Pierson et Fovet, d'une part, et du sieur Olive, d'autre part, sont déclarées irrecevables.<br/>
Article 2 :<br/>
la présente décision sera notifiée à l'Assemblée nationale.         
</CONTENU>
</BLOC_TEXTUEL>
<SAISINES>
<CONTENU/>
</SAISINES>
<OBSERVATIONS>
<CONTENU/>
</OBSERVATIONS>
</TEXTE>
</TEXTE_JURI_CONSTIT>
